json2csv/__init__.py
json2csv/cli.py
json2csv/csv_data.py
json2csv/json_schema.py
json_schema_to_csv-0.1.0.dist-info/WHEEL
json_schema_to_csv-0.1.0.dist-info/METADATA
json_schema_to_csv-0.1.0.dist-info/RECORD
