Metadata-Version: 2.1
Name: json-schema-to-csv
Version: 0.1.0
Summary: 
Author: Łukasz Bacik
Author-email: mail@luka.sh
Requires-Python: >=3.9,<4.0
Classifier: Programming Language :: Python :: 3
Classifier: Programming Language :: Python :: 3.9
Classifier: Programming Language :: Python :: 3.10
Classifier: Programming Language :: Python :: 3.11
Requires-Dist: jsonschema (>=4.17.3,<5.0.0)
